[
    {
        "filename": "huzongyao-_-JChineseChess.json",
        "published_at": "2019-05-07T09:58:17Z",
        "google_play_reviews": [
            {
                "reviewId": "8fe22883-7ac8-4064-bc99-a5d8fd5b4d06",
                "userName": "A Google user",
                "userImage": "https://play-lh.googleusercontent.com/EGemoI2NTXmTsBVtJqk8jxF9rh8ApRWfsIMQSt2uE4OcpQqbFu7f7NbTK05lx80nuSijCz7sc3a277R67g",
                "content": "ai so weak",
                "score": 1,
                "thumbsUpCount": 1,
                "reviewCreatedVersion": "1.0.3",
                "at": "2019-08-11 01:31:54",
                "replyContent": null,
                "repliedAt": "None"
            }
        ]
    }
]