[
    {
        "filename": "midhunhk-_-message-counter.json",
        "published_at": "2019-05-11T22:37:20Z",
        "google_play_reviews": [
            {
                "reviewId": "5b6b2c42-4d7e-48af-bb26-056f3ef92de8",
                "userName": "Badal Thakur",
                "userImage": "https://play-lh.googleusercontent.com/a-/ALV-UjWQ_SLiU4Zn6fr6dgrSWCnWWP9NkyeSgRZKcVUhp270tg",
                "content": "Before use this please tell me this app secure my privacy",
                "score": 1,
                "thumbsUpCount": 1,
                "reviewCreatedVersion": "4.1.1",
                "at": "2020-09-03 08:54:17",
                "replyContent": "Yes, please read the privacy policy.",
                "repliedAt": "2020-09-21 00:48:57"
            },
            {
                "reviewId": "84b7176f-775a-4be9-bcde-4328b4917915",
                "userName": "Dominik Mojto",
                "userImage": "https://play-lh.googleusercontent.com/a/ACg8ocJpWmTA7A1sFAMSIpNiPc8GWIUzSu2imbl3fapSqeVVug=mo",
                "content": "Useless",
                "score": 1,
                "thumbsUpCount": 0,
                "reviewCreatedVersion": "4.1.1",
                "at": "2020-06-21 11:03:00",
                "replyContent": null,
                "repliedAt": "None"
            },
            {
                "reviewId": "7446c25a-8915-4142-8fc2-b66c3da5231a",
                "userName": "A Google user",
                "userImage": "https://play-lh.googleusercontent.com/EGemoI2NTXmTsBVtJqk8jxF9rh8ApRWfsIMQSt2uE4OcpQqbFu7f7NbTK05lx80nuSijCz7sc3a277R67g",
                "content": "Frzi h",
                "score": 1,
                "thumbsUpCount": 0,
                "reviewCreatedVersion": "4.1.1",
                "at": "2020-03-16 17:42:03",
                "replyContent": null,
                "repliedAt": "None"
            },
            {
                "reviewId": "43182597-54c9-43cd-b7f3-fb169c0078d4",
                "userName": "A Google user",
                "userImage": "https://play-lh.googleusercontent.com/EGemoI2NTXmTsBVtJqk8jxF9rh8ApRWfsIMQSt2uE4OcpQqbFu7f7NbTK05lx80nuSijCz7sc3a277R67g",
                "content": "Can't download it!!!",
                "score": 1,
                "thumbsUpCount": 0,
                "reviewCreatedVersion": "4.1.1",
                "at": "2020-02-23 23:17:47",
                "replyContent": null,
                "repliedAt": "None"
            },
            {
                "reviewId": "904e4c40-17de-4c62-a84a-d8113e3039d2",
                "userName": "A Google user",
                "userImage": "https://play-lh.googleusercontent.com/EGemoI2NTXmTsBVtJqk8jxF9rh8ApRWfsIMQSt2uE4OcpQqbFu7f7NbTK05lx80nuSijCz7sc3a277R67g",
                "content": "boring app",
                "score": 1,
                "thumbsUpCount": 0,
                "reviewCreatedVersion": "4.1.1",
                "at": "2019-12-19 09:48:59",
                "replyContent": null,
                "repliedAt": "None"
            },
            {
                "reviewId": "66c714e4-743e-46d8-a07e-b51b363b137d",
                "userName": "A Google user",
                "userImage": "https://play-lh.googleusercontent.com/EGemoI2NTXmTsBVtJqk8jxF9rh8ApRWfsIMQSt2uE4OcpQqbFu7f7NbTK05lx80nuSijCz7sc3a277R67g",
                "content": "mad appp",
                "score": 1,
                "thumbsUpCount": 0,
                "reviewCreatedVersion": "4.1.1",
                "at": "2019-07-30 16:14:22",
                "replyContent": null,
                "repliedAt": "None"
            },
            {
                "reviewId": "0861a3db-c7e4-424b-996c-abc9416abfae",
                "userName": "A Google user",
                "userImage": "https://play-lh.googleusercontent.com/EGemoI2NTXmTsBVtJqk8jxF9rh8ApRWfsIMQSt2uE4OcpQqbFu7f7NbTK05lx80nuSijCz7sc3a277R67g",
                "content": "bad",
                "score": 1,
                "thumbsUpCount": 0,
                "reviewCreatedVersion": "4.1.1",
                "at": "2019-06-29 04:19:57",
                "replyContent": null,
                "repliedAt": "None"
            }
        ]
    },
    {
        "filename": "midhunhk-_-message-counter.json",
        "published_at": "2018-10-11T16:35:56Z",
        "google_play_reviews": [
            {
                "reviewId": "4e38dc14-8b09-4d16-aa15-36d57d2ac777",
                "userName": "A Google user",
                "userImage": "https://play-lh.googleusercontent.com/EGemoI2NTXmTsBVtJqk8jxF9rh8ApRWfsIMQSt2uE4OcpQqbFu7f7NbTK05lx80nuSijCz7sc3a277R67g",
                "content": "app counting sms properly for saved contacts only and not unknown numbers sms. As well no count for success or failed delivery messafes.",
                "score": 3,
                "thumbsUpCount": 23,
                "reviewCreatedVersion": "4.0.2",
                "at": "2018-12-21 14:31:32",
                "replyContent": "Hi Suryakant, thanks for your review. The messages sent count is for numbers in your contacts as well as any other. We cannot detect if a message was delivered successfully or not as the messages are not sent through this app.",
                "repliedAt": "2018-12-22 02:10:17"
            },
            {
                "reviewId": "563e63c2-eb29-447c-9726-d260cbf0688f",
                "userName": "A Google user",
                "userImage": "https://play-lh.googleusercontent.com/EGemoI2NTXmTsBVtJqk8jxF9rh8ApRWfsIMQSt2uE4OcpQqbFu7f7NbTK05lx80nuSijCz7sc3a277R67g",
                "content": "This app is good. I used it for long days. But recently I have watched something unusual. I am using postpaid number. So counting of sent message is very much important for me for my billing purpose. On last day I found that this message counter is showing 3 messages extra, while I am sure that I have not sent those extra 3 messages. In fact other message counter app is also showing the correct statistics. What may be the reason? Please look into the matter and solve it.  Additional information: I have received 3 OTP related message on that day in my inbox. Can these be wrongly reflected as sent messages?",
                "score": 3,
                "thumbsUpCount": 46,
                "reviewCreatedVersion": "4.0.2",
                "at": "2018-12-18 03:14:03",
                "replyContent": "Hi Abhirup, thanks for your detailed description. I will certainly look into the issue you faced. Please observe of you notice further irregularities. The received messages shouldn't reflect as sent message. \n\nCould you try restarting your phone, or force close and reopen the app.",
                "repliedAt": "2018-12-19 02:28:52"
            },
            {
                "reviewId": "7d78b831-5da2-4975-b49b-c160fd0b8898",
                "userName": "A Google user",
                "userImage": "https://play-lh.googleusercontent.com/EGemoI2NTXmTsBVtJqk8jxF9rh8ApRWfsIMQSt2uE4OcpQqbFu7f7NbTK05lx80nuSijCz7sc3a277R67g",
                "content": "5 stars. Congrats 🙂",
                "score": 5,
                "thumbsUpCount": 17,
                "reviewCreatedVersion": "4.0.2",
                "at": "2018-10-30 15:41:30",
                "replyContent": "Please check out the latest version. You should see sent and received message counts per contact",
                "repliedAt": "2018-10-30 15:36:52"
            }
        ]
    },
    {
        "filename": "midhunhk-_-message-counter.json",
        "published_at": "2018-09-15T18:59:14Z",
        "google_play_reviews": [
            {
                "reviewId": "e474fce1-cfe0-448b-9032-71f0ba270c0a",
                "userName": "A Google user",
                "userImage": "https://play-lh.googleusercontent.com/EGemoI2NTXmTsBVtJqk8jxF9rh8ApRWfsIMQSt2uE4OcpQqbFu7f7NbTK05lx80nuSijCz7sc3a277R67g",
                "content": "Very easy to use and really helpful for me. It works on any messaging apps. Loved it.",
                "score": 5,
                "thumbsUpCount": 22,
                "reviewCreatedVersion": "4.0.1",
                "at": "2018-09-26 08:42:10",
                "replyContent": "Thank you for your review and glad that you find it useful.",
                "repliedAt": "2018-09-26 12:04:48"
            }
        ]
    },
    {
        "filename": "midhunhk-_-message-counter.json",
        "published_at": "2017-11-26T10:46:22Z",
        "google_play_reviews": [
            {
                "reviewId": "5dd6241a-e905-402a-b17d-96eeac08f4c2",
                "userName": "A Google user",
                "userImage": "https://play-lh.googleusercontent.com/EGemoI2NTXmTsBVtJqk8jxF9rh8ApRWfsIMQSt2uE4OcpQqbFu7f7NbTK05lx80nuSijCz7sc3a277R67g",
                "content": "What I wanted!!! Kudos !!!",
                "score": 5,
                "thumbsUpCount": 2,
                "reviewCreatedVersion": "3.3.0",
                "at": "2018-09-24 16:50:00",
                "replyContent": "Thank you, happy to know that you are finding the app useful",
                "repliedAt": "2018-09-25 11:39:52"
            }
        ]
    },
    {
        "filename": "midhunhk-_-message-counter.json",
        "published_at": "2017-08-06T17:51:48Z",
        "google_play_reviews": []
    },
    {
        "filename": "midhunhk-_-message-counter.json",
        "published_at": "2017-05-14T05:41:54Z",
        "google_play_reviews": [
            {
                "reviewId": "fd97b20f-0633-41ed-b57c-aafe82b05752",
                "userName": "A Google user",
                "userImage": "https://play-lh.googleusercontent.com/EGemoI2NTXmTsBVtJqk8jxF9rh8ApRWfsIMQSt2uE4OcpQqbFu7f7NbTK05lx80nuSijCz7sc3a277R67g",
                "content": "Nice app",
                "score": 5,
                "thumbsUpCount": 13,
                "reviewCreatedVersion": "3.2.0",
                "at": "2017-07-09 11:18:57",
                "replyContent": "Thanks for the Review. Hope you are finding this app useful.",
                "repliedAt": "2017-07-09 17:04:29"
            },
            {
                "reviewId": "df7185b4-b168-4684-84a4-5be3b55ab5a5",
                "userName": "A Google user",
                "userImage": "https://play-lh.googleusercontent.com/EGemoI2NTXmTsBVtJqk8jxF9rh8ApRWfsIMQSt2uE4OcpQqbFu7f7NbTK05lx80nuSijCz7sc3a277R67g",
                "content": "its good but is limmited to sms  there must be an option for other messaging app like messenger",
                "score": 5,
                "thumbsUpCount": 12,
                "reviewCreatedVersion": "3.2.0",
                "at": "2017-07-06 05:47:09",
                "replyContent": "Thanks for the Review. Hope you are finding this app useful. This app tracks SMS es sent from your Android device.",
                "repliedAt": "2017-07-09 17:05:05"
            }
        ]
    }
]