[
    {
        "filename": "sunilpaulmathew-_-Translator.json",
        "published_at": "2022-12-10T08:43:21Z",
        "google_play_reviews": []
    },
    {
        "filename": "sunilpaulmathew-_-Translator.json",
        "published_at": "2021-12-18T21:40:52Z",
        "google_play_reviews": []
    },
    {
        "filename": "sunilpaulmathew-_-Translator.json",
        "published_at": "2021-10-16T15:59:57Z",
        "google_play_reviews": []
    },
    {
        "filename": "sunilpaulmathew-_-Translator.json",
        "published_at": "2021-06-05T16:31:08Z",
        "google_play_reviews": [
            {
                "reviewId": "b94eb414-5b99-4d89-abf1-8ffb014c05c6",
                "userName": "Hakret Code",
                "userImage": "https://play-lh.googleusercontent.com/a/ACg8ocIHeQ5SK3rbyV7_GGDKmSWb6OKbQTnQ9PyPfHjxXwQy=mo",
                "content": "Excelent",
                "score": 5,
                "thumbsUpCount": 0,
                "reviewCreatedVersion": "v0.15",
                "at": "2021-06-21 16:10:09",
                "replyContent": "Thank You",
                "repliedAt": "2021-06-21 17:23:33"
            }
        ]
    },
    {
        "filename": "sunilpaulmathew-_-Translator.json",
        "published_at": "2021-04-04T13:58:05Z",
        "google_play_reviews": [
            {
                "reviewId": "c7058c22-6d4f-4665-a46e-d4e66bf09699",
                "userName": "Shawn Schweitzer",
                "userImage": "https://play-lh.googleusercontent.com/a-/ALV-UjX6hV56aI0xDLgqu_HBySLev8rOoVeE65wo9CCJmWuCwrA",
                "content": "Didn't recognize file types or extensions",
                "score": 1,
                "thumbsUpCount": 0,
                "reviewCreatedVersion": "v0.13",
                "at": "2021-05-05 15:16:59",
                "replyContent": "Please try with a different file manager (recommend: Material Files).",
                "repliedAt": "2021-05-05 15:51:50"
            }
        ]
    },
    {
        "filename": "sunilpaulmathew-_-Translator.json",
        "published_at": "2021-03-14T22:56:43Z",
        "google_play_reviews": []
    },
    {
        "filename": "sunilpaulmathew-_-Translator.json",
        "published_at": "2021-02-15T23:28:27Z",
        "google_play_reviews": []
    },
    {
        "filename": "sunilpaulmathew-_-Translator.json",
        "published_at": "2021-02-02T06:00:51Z",
        "google_play_reviews": []
    },
    {
        "filename": "sunilpaulmathew-_-Translator.json",
        "published_at": "2021-01-15T21:14:00Z",
        "google_play_reviews": []
    }
]