[
    {
        "filename": "tasomaniac-_-DevWidget.json",
        "published_at": "2019-06-02T19:45:12Z",
        "google_play_reviews": []
    },
    {
        "filename": "tasomaniac-_-DevWidget.json",
        "published_at": "2019-01-23T19:24:07Z",
        "google_play_reviews": []
    },
    {
        "filename": "tasomaniac-_-DevWidget.json",
        "published_at": "2018-10-15T23:15:19Z",
        "google_play_reviews": []
    },
    {
        "filename": "tasomaniac-_-DevWidget.json",
        "published_at": "2018-10-15T23:12:05Z",
        "google_play_reviews": []
    },
    {
        "filename": "tasomaniac-_-DevWidget.json",
        "published_at": "2018-08-12T11:53:45Z",
        "google_play_reviews": []
    },
    {
        "filename": "tasomaniac-_-DevWidget.json",
        "published_at": "2018-01-21T22:32:24Z",
        "google_play_reviews": []
    }
]