[
    {
        "filename": "zoff99-_-ToxAndroidRefImpl.json",
        "published_at": "2023-02-10T16:53:12Z",
        "google_play_reviews": []
    },
    {
        "filename": "zoff99-_-ToxAndroidRefImpl.json",
        "published_at": "2023-02-04T08:06:30Z",
        "google_play_reviews": []
    },
    {
        "filename": "zoff99-_-ToxAndroidRefImpl.json",
        "published_at": "2023-01-27T15:53:19Z",
        "google_play_reviews": []
    },
    {
        "filename": "zoff99-_-ToxAndroidRefImpl.json",
        "published_at": "2023-01-06T10:00:45Z",
        "google_play_reviews": []
    },
    {
        "filename": "zoff99-_-ToxAndroidRefImpl.json",
        "published_at": "2022-12-28T08:48:11Z",
        "google_play_reviews": []
    },
    {
        "filename": "zoff99-_-ToxAndroidRefImpl.json",
        "published_at": "2022-11-11T13:46:22Z",
        "google_play_reviews": []
    },
    {
        "filename": "zoff99-_-ToxAndroidRefImpl.json",
        "published_at": "2022-10-20T17:39:42Z",
        "google_play_reviews": []
    },
    {
        "filename": "zoff99-_-ToxAndroidRefImpl.json",
        "published_at": "2022-09-20T17:21:22Z",
        "google_play_reviews": []
    },
    {
        "filename": "zoff99-_-ToxAndroidRefImpl.json",
        "published_at": "2022-09-17T12:09:43Z",
        "google_play_reviews": []
    },
    {
        "filename": "zoff99-_-ToxAndroidRefImpl.json",
        "published_at": "2022-08-18T14:35:14Z",
        "google_play_reviews": []
    },
    {
        "filename": "zoff99-_-ToxAndroidRefImpl.json",
        "published_at": "2022-08-07T19:16:28Z",
        "google_play_reviews": []
    },
    {
        "filename": "zoff99-_-ToxAndroidRefImpl.json",
        "published_at": "2022-07-29T16:30:59Z",
        "google_play_reviews": []
    },
    {
        "filename": "zoff99-_-ToxAndroidRefImpl.json",
        "published_at": "2022-07-13T12:18:55Z",
        "google_play_reviews": []
    },
    {
        "filename": "zoff99-_-ToxAndroidRefImpl.json",
        "published_at": "2022-06-24T18:21:01Z",
        "google_play_reviews": []
    },
    {
        "filename": "zoff99-_-ToxAndroidRefImpl.json",
        "published_at": "2022-06-19T17:33:55Z",
        "google_play_reviews": []
    },
    {
        "filename": "zoff99-_-ToxAndroidRefImpl.json",
        "published_at": "2022-04-17T07:39:52Z",
        "google_play_reviews": []
    },
    {
        "filename": "zoff99-_-ToxAndroidRefImpl.json",
        "published_at": "2022-03-29T13:21:40Z",
        "google_play_reviews": []
    },
    {
        "filename": "zoff99-_-ToxAndroidRefImpl.json",
        "published_at": "2022-02-22T18:37:53Z",
        "google_play_reviews": [
            {
                "reviewId": "e36e86b1-7b75-4a36-a11a-674c35856186",
                "userName": "Baron Samedi",
                "userImage": "https://play-lh.googleusercontent.com/a-/ALV-UjUHjsBP0fzzTfwMIcMf2qCP_RbQt39FekaeFlXiWfFBjw",
                "content": "Stable on Android 7 and 8 now(12/3/22). I thank the developers for their prompt response to reported past problems. I have found this to be the best mobile TOX client with respect to functionality and customer service. Would unreservedly recommend.",
                "score": 4,
                "thumbsUpCount": 0,
                "reviewCreatedVersion": "1.0.142",
                "at": "2022-03-12 03:00:57",
                "replyContent": "the bug should be fixed with 1.0.157",
                "repliedAt": "2022-07-11 10:44:02"
            }
        ]
    },
    {
        "filename": "zoff99-_-ToxAndroidRefImpl.json",
        "published_at": "2022-02-11T16:50:12Z",
        "google_play_reviews": []
    },
    {
        "filename": "zoff99-_-ToxAndroidRefImpl.json",
        "published_at": "2022-02-10T14:48:14Z",
        "google_play_reviews": []
    },
    {
        "filename": "zoff99-_-ToxAndroidRefImpl.json",
        "published_at": "2022-02-05T20:02:40Z",
        "google_play_reviews": []
    },
    {
        "filename": "zoff99-_-ToxAndroidRefImpl.json",
        "published_at": "2022-01-17T19:12:14Z",
        "google_play_reviews": []
    },
    {
        "filename": "zoff99-_-ToxAndroidRefImpl.json",
        "published_at": "2022-01-09T12:08:26Z",
        "google_play_reviews": []
    },
    {
        "filename": "zoff99-_-ToxAndroidRefImpl.json",
        "published_at": "2021-10-24T12:10:54Z",
        "google_play_reviews": [
            {
                "reviewId": "406757f8-b938-4da6-8c70-4e46887dbff8",
                "userName": "Tài Huỳnh Văn",
                "userImage": "https://play-lh.googleusercontent.com/a/ACg8ocLb4Hp-LJVVgdyQxhRNXJ_dsP-Zpe6a7qEkgVTxgZ3XgQ=mo",
                "content": "Thank you for a good app. I love this old-fashioned UI. Feel peace, not bloat. btw, i use Artix.",
                "score": 5,
                "thumbsUpCount": 1,
                "reviewCreatedVersion": "1.0.122",
                "at": "2021-12-20 12:50:35",
                "replyContent": null,
                "repliedAt": "None"
            },
            {
                "reviewId": "5368b140-e6ac-407f-9a69-74f683f980d6",
                "userName": "Behzad Daneshpour (Noyzen)",
                "userImage": "https://play-lh.googleusercontent.com/a-/ALV-UjVjvVa9aStdgnFKF_4XtaO8ZykAYYYloFqPTw3WZGWQb4o",
                "content": "Seems like the only Android Tox client which have voice and video call support and have an option to work with orbot and its Not outdated. a Dark Theme needed btw... Good Job :)",
                "score": 4,
                "thumbsUpCount": 4,
                "reviewCreatedVersion": "1.0.122",
                "at": "2021-10-26 22:27:38",
                "replyContent": "Dark Theme is in the works ...",
                "repliedAt": "2022-03-12 07:55:58"
            }
        ]
    },
    {
        "filename": "zoff99-_-ToxAndroidRefImpl.json",
        "published_at": "2021-10-05T14:28:46Z",
        "google_play_reviews": []
    },
    {
        "filename": "zoff99-_-ToxAndroidRefImpl.json",
        "published_at": "2021-10-01T16:57:51Z",
        "google_play_reviews": []
    },
    {
        "filename": "zoff99-_-ToxAndroidRefImpl.json",
        "published_at": "2021-09-24T12:59:19Z",
        "google_play_reviews": []
    },
    {
        "filename": "zoff99-_-ToxAndroidRefImpl.json",
        "published_at": "2021-09-09T15:31:49Z",
        "google_play_reviews": []
    },
    {
        "filename": "zoff99-_-ToxAndroidRefImpl.json",
        "published_at": "2021-09-03T07:17:12Z",
        "google_play_reviews": []
    }
]